datasette_clone/__init__.py
datasette_clone/cli.py
datasette_clone-0.5.dist-info/LICENSE
datasette_clone-0.5.dist-info/METADATA
datasette_clone-0.5.dist-info/WHEEL
datasette_clone-0.5.dist-info/entry_points.txt
datasette_clone-0.5.dist-info/top_level.txt
datasette_clone-0.5.dist-info/RECORD
