Metadata-Version: 2.1
Name: datasette-clone
Version: 0.5
Summary: Create a local copy of database files from a Datasette instance
Home-page: https://github.com/simonw/datasette-clone
Author: Simon Willison
License: Apache License, Version 2.0
Platform: UNKNOWN
Requires-Dist: requests
Requires-Dist: click
Provides-Extra: test
Requires-Dist: pytest ; extra == 'test'
Requires-Dist: requests-mock ; extra == 'test'
